ProcessingQt/__init__.py
ProcessingQt/constants.py
ProcessingQt/primitives.py
ProcessingQt/processing.py
ProcessingQt/renderer2d.py
ProcessingQt/sketch.py
ProcessingQt/transforms.py
ProcessingQt/userspace.py
ProcessingQt/vertex.py
ProcessingQt-1.0.0.dist-info/LICENSE
ProcessingQt-1.0.0.dist-info/METADATA
ProcessingQt-1.0.0.dist-info/WHEEL
ProcessingQt-1.0.0.dist-info/top_level.txt
ProcessingQt-1.0.0.dist-info/RECORD
