Metadata-Version: 2.1
Name: ProcessingQt
Version: 1.0.0
Summary: Python library for Processing software. Built on top of Qt5
Home-page: https://github.com/parsoyaarihant/ProcessingQt
Author: Arihant Parsoya
Author-email: parsoyaarihant@gmail.com
License: UNKNOWN
Platform: UNKNOWN
Classifier: Programming Language :: Python :: 3
Classifier: Intended Audience :: Developers
Classifier: Intended Audience :: Education
Classifier: Topic :: Artistic Software
Classifier: Topic :: Education
Classifier: Topic :: Multimedia
Classifier: Topic :: Multimedia :: Graphics
Classifier: License :: OSI Approved :: GNU General Public License v3 (GPLv3)
Classifier: Operating System :: OS Independent
Requires-Python: >=3.6
Requires-Dist: PyQt5
